_cbcpy.so
cbcpy.py
cbcpy-2.10.3a2.dist-info/METADATA
cbcpy-2.10.3a2.dist-info/WHEEL
cbcpy-2.10.3a2.dist-info/RECORD
cbcpy-2.10.3a2.dist-info/top_level.txt
