Metadata-Version: 2.1
Name: cbcpy
Version: 2.10.3a2
Summary: Coin-or CBC native interface for Python
Home-page: https://git.patrikdufresne.com/pdsl/cbcpy
Author: Patrik Dufresne
Author-email: info@patrikdufresne.com
License: LGPL
Keywords: coin-or cbc
Platform: UNKNOWN
Classifier: Development Status :: 3 - Alpha
Classifier: Intended Audience :: Developers
Classifier: License :: OSI Approved :: GNU Lesser General Public License v3 (LGPLv3)
Classifier: Programming Language :: Python :: 2
Classifier: Programming Language :: Python :: 2.7
Classifier: Programming Language :: Python :: 3
Classifier: Programming Language :: Python :: 3.5
Classifier: Programming Language :: Python :: 3.6
Classifier: Programming Language :: Python :: 3.7
Requires-Python: >=2.7, !=3.0.*, !=3.1.*, !=3.2.*, !=3.3.*, !=3.4.*, <4
